mockeval/__init__.py
mockeval-0.1.3.dist-info/LICENSE
mockeval-0.1.3.dist-info/WHEEL
mockeval-0.1.3.dist-info/METADATA
mockeval-0.1.3.dist-info/RECORD
