Metadata-Version: 2.1
Name: mockeval
Version: 0.1.3
Summary: Cursed lambdas because yes
License: Unlicense
Author: CircuitSacul
Author-email: circuitsacul@gmail.com
Requires-Python: >=3.8,<4.0
Classifier: License :: Other/Proprietary License
Classifier: Programming Language :: Python :: 3
Classifier: Programming Language :: Python :: 3.8
Classifier: Programming Language :: Python :: 3.9
Classifier: Programming Language :: Python :: 3.10
Classifier: Programming Language :: Python :: 3.11
